MANIFEST.in
README.rst
setup.cfg
setup.py
MySimpleGUI/MySimpleGUI.py
MySimpleGUI/__init__.py
MySimpleGUI/changelog.txt
MySimpleGUI.egg-info/PKG-INFO
MySimpleGUI.egg-info/SOURCES.txt
MySimpleGUI.egg-info/dependency_links.txt
MySimpleGUI.egg-info/top_level.txt