Metadata-Version: 1.1
Name: MySimpleGUI
Version: 1.1.11
Summary: MySimpleGUI
Home-page: https://github.com/salabim/salabim
Author: Ruud van der Ham
Author-email: info@salabim.org
License: UNKNOWN
Download-URL: https://github.com/salabim/MySimpleGUI
Keywords: GUI
Platform: UNKNOWN
